LICENSE.txt
MANIFEST.in
README.md
setup.cfg
setup.py
aws_cdk_constructs/__init__.py
aws_cdk_constructs/utils.py
aws_cdk_constructs.egg-info/PKG-INFO
aws_cdk_constructs.egg-info/SOURCES.txt
aws_cdk_constructs.egg-info/dependency_links.txt
aws_cdk_constructs.egg-info/requires.txt
aws_cdk_constructs.egg-info/top_level.txt
aws_cdk_constructs/api/__init__.py
aws_cdk_constructs/api/api.py
aws_cdk_constructs/bucket/__init__.py
aws_cdk_constructs/bucket/auth_flow.py
aws_cdk_constructs/bucket/base_edge_constructs.py
aws_cdk_constructs/bucket/bucket.py
aws_cdk_constructs/bucket/configuration.py
aws_cdk_constructs/bucket/edge_function.py
aws_cdk_constructs/bucket/edge_role.py
aws_cdk_constructs/bucket/log_level.py
aws_cdk_constructs/bucket/secret_generator.py
aws_cdk_constructs/bucket/with_configuration.py
aws_cdk_constructs/database/__init__.py
aws_cdk_constructs/database/database.py
aws_cdk_constructs/database/types.py
aws_cdk_constructs/database/_types/__init__.py
aws_cdk_constructs/database/_types/document.py
aws_cdk_constructs/database/_types/graph.py
aws_cdk_constructs/database/_types/relational.py
aws_cdk_constructs/ecs/__init__.py
aws_cdk_constructs/ecs/cluster.py
aws_cdk_constructs/ecs/fargate_validator.py
aws_cdk_constructs/ecs/microservice.py
aws_cdk_constructs/efs/__init__.py
aws_cdk_constructs/efs/volume.py
aws_cdk_constructs/lambdas/add-index/index.js
aws_cdk_constructs/lambdas/add-index/index.js.map
aws_cdk_constructs/lambdas/check-auth/index.js
aws_cdk_constructs/lambdas/check-auth/index.js.LICENSE.txt
aws_cdk_constructs/lambdas/check-auth/index.js.map
aws_cdk_constructs/lambdas/parse-auth/index.js
aws_cdk_constructs/lambdas/parse-auth/index.js.LICENSE.txt
aws_cdk_constructs/lambdas/parse-auth/index.js.map
aws_cdk_constructs/lambdas/refresh-auth/index.js
aws_cdk_constructs/lambdas/refresh-auth/index.js.LICENSE.txt
aws_cdk_constructs/lambdas/refresh-auth/index.js.map
aws_cdk_constructs/lambdas/secret-generator/index.js
aws_cdk_constructs/lambdas/secret-generator/index.js.map
aws_cdk_constructs/lambdas/sign-out/index.js
aws_cdk_constructs/lambdas/sign-out/index.js.LICENSE.txt
aws_cdk_constructs/lambdas/sign-out/index.js.map
