Metadata-Version: 2.4
Name: aws_cdk_constructs
Version: 2.43.0
Summary: AWS CDK constructs
Home-page: https://bitbucket.org/cioapps/aws-cdk-constructs
Author: author
Author-email: author@foa.org
Classifier: Development Status :: 4 - Beta
Classifier: Intended Audience :: Developers
Classifier: License :: OSI Approved :: Apache Software License
Classifier: Programming Language :: JavaScript
Classifier: Programming Language :: Python :: 3 :: Only
Classifier: Programming Language :: Python :: 3.6
Classifier: Programming Language :: Python :: 3.7
Classifier: Programming Language :: Python :: 3.8
Classifier: Topic :: Software Development :: Code Generators
Classifier: Topic :: Utilities
Classifier: Typing :: Typed
Requires-Python: >=3.6
License-File: LICENSE.txt
Requires-Dist: aws-cdk-lib==2.206.0
Requires-Dist: aws-cdk.aws-neptune-alpha==2.206.0a0
Requires-Dist: constructs<11.0.0,>=10.0.0
Requires-Dist: boto3==1.36.25
Requires-Dist: pydantic==2.10.6
Dynamic: author
Dynamic: author-email
Dynamic: classifier
Dynamic: description
Dynamic: description-content-type
Dynamic: home-page
Dynamic: license-file
Dynamic: requires-dist
Dynamic: requires-python
Dynamic: summary
